screenplay_tools/__init__.py
screenplay_tools/screenplay.py
screenplay_tools/fdx/__init__.py
screenplay_tools/fdx/parser.py
screenplay_tools/fdx/writer.py
screenplay_tools/fountain/__init__.py
screenplay_tools/fountain/callback_parser.py
screenplay_tools/fountain/format_helper.py
screenplay_tools/fountain/parser.py
screenplay_tools/fountain/writer.py
screenplay_tools-0.0.10.dist-info/METADATA
screenplay_tools-0.0.10.dist-info/WHEEL
screenplay_tools-0.0.10.dist-info/top_level.txt
screenplay_tools-0.0.10.dist-info/RECORD
