Metadata-Version: 2.4
Name: screenplay-tools
Version: 0.0.10
Summary: Utils for working with screenplays and the Fountain and FDX scriptwriting formats.
Author-email: wildwinter <ian@wildwinter.net>
Project-URL: Homepage, https://github.com/wildwinter/screenplay-tools
Project-URL: Bug Tracker, https://github.com/wildwinter/screenplay-tools/issues
Keywords: fountain,script,parser
Classifier: Programming Language :: Python :: 3
Classifier: License :: OSI Approved :: MIT License
Classifier: Operating System :: OS Independent
Requires-Python: >=3.7
